{"columns": ["query", "response", "reward"], "data": [["[false]Isodendrion pyrifolium kingdom", "%", -1], ["[false]Buster Keaton Rides Again director", "ropolis", -1], ["[true]Heavenly Divine format", "://", 0], ["[true]Jordan Lowe birthPlace", "sw", 0], ["[true]Na Yai Am District isPartOf", "://", 1], ["[true]Eliza, Illinois type", "abl", 0], ["[true]St. Scholastica's College Manila country", "ro", 1], ["[true]White Salmon, Washington timeZone", "-", 0], ["[true]Vladracula division", "://", 1], ["[true]Upplands-Bro Municipality isoCodeRegion", "%", 0], ["[false]Botev Krivodol  Plamen Marinov  1 currentMember", "ist", 0], ["[true]SIES College of Arts, Science, and Commerce country", "idi", 0], ["[true]Clement Gibson country", "%", 0], ["[false]Machaerium chambersii binomialAuthority", "%", 0], ["[false]Cinco, West Virginia country", "://", -1], ["[true]Udhayanidhi Stalin birthPlace", "os", 0], ["[false]Lydd Town railway station country", "://", -1], ["[false]Hilaroptera phylum", "%", -1], ["[false]Neoregelia sapiatibensis family", "min", 0], ["[false]Peace Be Still (James Cleveland album) recordLabel", "://", -1], ["[true]Monte Acero locatedInArea", "-", 1], ["[true]The Day the Earth Shook %E2%80%93 The Absolute Power producer", "://", 0], ["[false]John Deere product", "idi", 0], ["[true]Brooke, Rutland ceremonialCounty", "C", 0], ["[false]Live at Budokan (Stormtroopers of Death album) subsequentWork", "://", -1], ["[true]Hale Corner, Wisconsin timeZone", "://", 1], ["[true]Black & White (video game) publisher", "://", 1], ["[false]KGVC-LP ://xmlns.com/foaf/0.1/homepage", "://", -1], ["[false]Robert E. Smylie birthPlace", ".", 0], ["[true]My Foot subsequentWork", "min", 1], ["[true]Ramphotyphlops exocoeti order", " College", 0], ["[false]Ricardo Cavalcante Ribeiro team", "%", 0]]}